django_riotjs_helper-0.1.1.dist-info/METADATA
django_riotjs_helper-0.1.1.dist-info/RECORD
django_riotjs_helper-0.1.1.dist-info/WHEEL
django_riotjs_helper-0.1.1.dist-info/top_level.txt
riotjs_helper/__init__.py
riotjs_helper/apps.py
riotjs_helper/tests.py
riotjs_helper/management/__init__.py
riotjs_helper/management/commands/__init__.py
riotjs_helper/management/commands/riot_tag.py
riotjs_helper/templates/riotjs_helper/riotjs_core.html
riotjs_helper/templates/riotjs_helper/riotjs_mount.html
riotjs_helper/templates/riotjs_helper/riotjs_setup.html
