Metadata-Version: 2.1
Name: django-riotjs-helper
Version: 0.1.1
Summary: A small, rudimentary helper app for RiotJS integration into django projects.
Home-page: https://github.com/weholt/django-riotjs-helper
Author: Thomas Weholt
Author-email: thomas@weholt.org
License: MIT
Keywords: django-riotjs-helper
Platform: UNKNOWN
Classifier: Development Status :: 3 - Alpha
Classifier: Framework :: Django :: 2.0
Classifier: Intended Audience :: Developers
Classifier: License :: OSI Approved :: BSD License
Classifier: Natural Language :: English
Classifier: Programming Language :: Python :: 2
Classifier: Programming Language :: Python :: 2.7
Classifier: Programming Language :: Python :: 3
Classifier: Programming Language :: Python :: 3.4
Classifier: Programming Language :: Python :: 3.5
Classifier: Programming Language :: Python :: 3.6
Requires-Dist: django
